fullscreen_message/__init__.py
fullscreen_message/main.py
fullscreen_message-1.0.0.dist-info/METADATA
fullscreen_message-1.0.0.dist-info/WHEEL
fullscreen_message-1.0.0.dist-info/entry_points.txt
fullscreen_message-1.0.0.dist-info/top_level.txt
fullscreen_message-1.0.0.dist-info/RECORD
