Metadata-Version: 2.4
Name: fullscreen-message
Version: 1.0.0
Summary: A command-line tool to show big messages across the entire screen in a GUI
Author-email: "@readwithai" <talwrii@googlemail.com>
License: MIT
Project-URL: Homepage, https://github.com/talwrii/fullscreen-message
Project-URL: Issues, https://github.com/talwrii/fullscreen-message/issues
Keywords: notification,message,fullscreen,alert,display
Classifier: Development Status :: 4 - Beta
Classifier: Intended Audience :: Developers
Classifier: Intended Audience :: End Users/Desktop
Classifier: License :: OSI Approved :: MIT License
Classifier: Operating System :: OS Independent
Classifier: Programming Language :: Python :: 3
Classifier: Programming Language :: Python :: 3.7
Classifier: Programming Language :: Python :: 3.8
Classifier: Programming Language :: Python :: 3.9
Classifier: Programming Language :: Python :: 3.10
Classifier: Programming Language :: Python :: 3.11
Classifier: Programming Language :: Python :: 3.12
Classifier: Topic :: Utilities
Requires-Python: >=3.7
